README.txt
setup.py
docs/HISTORY.txt
upfront/__init__.py
upfront.simplereferencefield.egg-info/PKG-INFO
upfront.simplereferencefield.egg-info/SOURCES.txt
upfront.simplereferencefield.egg-info/dependency_links.txt
upfront.simplereferencefield.egg-info/entry_points.txt
upfront.simplereferencefield.egg-info/namespace_packages.txt
upfront.simplereferencefield.egg-info/not-zip-safe
upfront.simplereferencefield.egg-info/requires.txt
upfront.simplereferencefield.egg-info/top_level.txt
upfront/simplereferencefield/README.txt
upfront/simplereferencefield/__init__.py
upfront/simplereferencefield/interfaces.py
upfront/simplereferencefield/simplereferencefield.py
upfront/simplereferencefield/tests.py
upfront/simplereferencefield/version.txt