Metadata-Version: 1.0
Name: upfront.simplereferencefield
Version: 0.5
Summary: Store references on an object and not in the reference catalog
Home-page: UNKNOWN
Author: Roche Compaan
Author-email: roche@upfrontsystems.co.za
License: GPL
Platform: UNKNOWN
Classifier: Programming Language :: Python
Classifier: Topic :: Software Development :: Libraries :: Python Modules
Classifier: Framework :: Zope2
Classifier: Framework :: Plone
